asdf_unit_schemas/__init__.py
asdf_unit_schemas/_version.py
asdf_unit_schemas-0.2.0.dist-info/LICENSE
asdf_unit_schemas-0.2.0.dist-info/METADATA
asdf_unit_schemas-0.2.0.dist-info/WHEEL
asdf_unit_schemas-0.2.0.dist-info/top_level.txt
asdf_unit_schemas-0.2.0.dist-info/RECORD
