Metadata-Version: 2.1
Name: asdf_unit_schemas
Version: 0.2.0
Summary: DEPRECATED: ASDF schemas for units
Author-email: The ASDF Developers <help@stsci.edu>
License: Copyright (c) 2021 Association of Universities for Research in Astronomy.
Project-URL: tracker, https://github.com/asdf-format/asdf-unit-schemas/issues
Project-URL: documentation, https://asdf-unit-schemas.readthedocs.io/en/stable
Project-URL: repository, https://github.com/asdf-format/asdf-unit-schemas
Classifier: Programming Language :: Python
Classifier: Programming Language :: Python :: 3
Classifier: Programming Language :: Python :: 3.8
Classifier: Programming Language :: Python :: 3.9
Classifier: Programming Language :: Python :: 3.10
Classifier: Development Status :: 5 - Production/Stable
Requires-Python: >=3.8
License-File: LICENSE
Provides-Extra: docs
Requires-Dist: tomli; extra == "docs"
Requires-Dist: sphinx; extra == "docs"
Requires-Dist: sphinx-rtd-theme; extra == "docs"
Provides-Extra: test
Requires-Dist: pytest; extra == "test"
Requires-Dist: asdf; extra == "test"
